TTFtoScratch/__init__.py
PyTTFontToScratch-0.0.1.dist-info/LICENSE
PyTTFontToScratch-0.0.1.dist-info/METADATA
PyTTFontToScratch-0.0.1.dist-info/WHEEL
PyTTFontToScratch-0.0.1.dist-info/top_level.txt
PyTTFontToScratch-0.0.1.dist-info/RECORD
